infinite_note/__init__.py
infinite_note/infinite_note.py
infinite_note/file/__init__.py
infinite_note/file/file_manager.py
infinite_note-0.3.0.dist-info/LICENSE
infinite_note-0.3.0.dist-info/METADATA
infinite_note-0.3.0.dist-info/WHEEL
infinite_note-0.3.0.dist-info/entry_points.txt
infinite_note-0.3.0.dist-info/top_level.txt
infinite_note-0.3.0.dist-info/RECORD
