Metadata-Version: 2.1
Name: infinite-note
Version: 0.3.0
Summary: 문제와 답을 입력하여 정답/오답을 관리하는 콘솔 프로그램
Home-page: https://offtheface.github.io/infinite-note
Author: offtheface
Author-email: rokany@cau.ac.kr
License: GNU General Public License (GPL)
Project-URL: Bug Tracker, https://github.com/offtheface/infinite-note/issues
Platform: macOS
Classifier: Programming Language :: Python :: 3
Classifier: License :: OSI Approved :: GNU General Public License (GPL)
Classifier: Operating System :: OS Independent
Requires-Python: >=3.6
License-File: LICENSE
